<?xml version="1.0" encoding="UTF-8"?>
<objects serializationModel="Studio.02.02.00">
	<object class="AudioFile" id="{505fe5fe-173b-42f5-96a0-64228f0a1fc8}">
		<property name="assetPath">
			<value>Temporary/kenney-interface/maximize_008.ogg</value>
		</property>
		<property name="frequencyInKHz">
			<value>44.0999985</value>
		</property>
		<property name="channelCount">
			<value>1</value>
		</property>
		<property name="length">
			<value>0.2253514739229025</value>
		</property>
		<relationship name="masterAssetFolder">
			<destination>{dba35553-9e0f-452d-8055-c8fc5948a18e}</destination>
		</relationship>
	</object>
</objects>
