<?xml version="1.0" encoding="UTF-8"?>
<objects serializationModel="Studio.02.02.00">
	<object class="AudioFile" id="{180a1d9f-5c32-42f2-ac74-2b1defac05d7}">
		<property name="assetPath">
			<value>SoundEffects/UI/FireworkHit.wav</value>
		</property>
		<property name="frequencyInKHz">
			<value>48</value>
		</property>
		<property name="channelCount">
			<value>1</value>
		</property>
		<property name="length">
			<value>0.98914583333333328</value>
		</property>
		<relationship name="masterAssetFolder">
			<destination>{dba35553-9e0f-452d-8055-c8fc5948a18e}</destination>
		</relationship>
	</object>
</objects>
